harbor/__init__.py
harbor/agents/base.py
harbor/agents/factory.py
harbor/agents/installed/aider.py
harbor/agents/installed/base.py
harbor/agents/installed/claude_code.py
harbor/agents/installed/cline/__init__.py
harbor/agents/installed/cline/cline.py
harbor/agents/installed/cline/install-cline.sh.j2
harbor/agents/installed/codex.py
harbor/agents/installed/cursor_cli.py
harbor/agents/installed/gemini_cli.py
harbor/agents/installed/goose.py
harbor/agents/installed/install-aider.sh.j2
harbor/agents/installed/install-claude-code.sh.j2
harbor/agents/installed/install-codex.sh.j2
harbor/agents/installed/install-cursor-cli.sh.j2
harbor/agents/installed/install-gemini-cli.sh.j2
harbor/agents/installed/install-goose.sh.j2
harbor/agents/installed/install-mini-swe-agent.sh.j2
harbor/agents/installed/install-opencode.sh.j2
harbor/agents/installed/install-openhands.sh.j2
harbor/agents/installed/install-qwen-code.sh.j2
harbor/agents/installed/install-swe-agent.sh.j2
harbor/agents/installed/mini_swe_agent.py
harbor/agents/installed/opencode.py
harbor/agents/installed/openhands.py
harbor/agents/installed/qwen_code.py
harbor/agents/installed/swe_agent.py
harbor/agents/nop.py
harbor/agents/oracle.py
harbor/agents/terminus_2/__init__.py
harbor/agents/terminus_2/asciinema_handler.py
harbor/agents/terminus_2/get-asciinema-timestamp.sh
harbor/agents/terminus_2/templates/terminus-json-plain.txt
harbor/agents/terminus_2/templates/terminus-xml-plain.txt
harbor/agents/terminus_2/templates/timeout.txt
harbor/agents/terminus_2/terminus_2.py
harbor/agents/terminus_2/terminus_json_plain_parser.py
harbor/agents/terminus_2/terminus_xml_plain_parser.py
harbor/agents/terminus_2/tmux_session.py
harbor/agents/utils.py
harbor/cli/adapter_wizard.py
harbor/cli/adapters.py
harbor/cli/admin/admin.py
harbor/cli/admin/docker-compose.build.yaml
harbor/cli/cache.py
harbor/cli/datasets.py
harbor/cli/debug_checker/__init__.py
harbor/cli/debug_checker/debug_checker.py
harbor/cli/debug_checker/debug_prompt.txt
harbor-0.1.43.dist-info/WHEEL
harbor-0.1.43.dist-info/entry_points.txt
harbor-0.1.43.dist-info/METADATA
harbor-0.1.43.dist-info/RECORD
