Metadata-Version: 2.3
Name: harbor
Version: 0.1.43
Summary: A framework for evaluating and optimizing agents and models using sandboxed environments.
Author: Alex Shaw
Author-email: Alex Shaw <alexgshaw64@gmail.com>
Requires-Dist: pydantic>=2.11.7
Requires-Dist: shortuuid>=1.0.13
Requires-Dist: typer>=0.16.0
Requires-Dist: requests>=2.32.4
Requires-Dist: pyyaml>=6.0.2
Requires-Dist: rich>=14.1.0
Requires-Dist: toml>=0.10.2
Requires-Dist: tenacity>=9.1.2
Requires-Dist: python-dotenv>=1.1.1
Requires-Dist: litellm>=1.80.8
Requires-Dist: jinja2>=3.1.6
Requires-Dist: dirhash>=0.5.0
Requires-Dist: dockerfile-parse>=2.0.1
Requires-Dist: e2b>=2.4.2
Requires-Dist: datasets>=4.4.1
Requires-Dist: runloop-api-client>=1.2.0
Requires-Dist: daytona>=0.121.0
Requires-Dist: kubernetes>=32.0.0
Requires-Dist: claude-agent-sdk>=0.1.17
Requires-Dist: supabase>=2.27.0
Requires-Dist: packaging>=25.0
Requires-Dist: fastapi>=0.128.0
Requires-Dist: uvicorn>=0.38.0
Requires-Dist: modal>=1.3.0.post1
Requires-Python: >=3.12
